utils/__init__.py
utils/agents_utils.py
utils/common.py
utils/env.py
utils/image.py
utils/llm_output_parser.py
utils/log.py
utils/path.py
utils/print_utils.py
utils/script_utils.py
utils/sqlmodel_utils.py
utils/token.py
utils/tool_cache.py
utils/openai_utils/__init__.py
utils/openai_utils/openai_utils.py
utils/openai_utils/simplified_client.py
utils/openai_utils/types.py
youtu_agent-0.1.2.dist-info/METADATA
youtu_agent-0.1.2.dist-info/WHEEL
youtu_agent-0.1.2.dist-info/licenses/LICENSE
youtu_agent-0.1.2.dist-info/RECORD
