Metadata-Version: 2.4
Name: youtu-agent
Version: 0.1.2
Summary: Youtu-Agent is a simple but powerful framework for building, running, and evaluating agents.
Project-URL: Homepage, https://github.com/TencentCloudADP/youtu-agent
Project-URL: Documentation, https://tencentcloudadp.github.io/youtu-agent/
Project-URL: Repository, https://github.com/TencentCloudADP/youtu-agent
Author-email: easonsshi <easonsshi@tencent.com>
License-Expression: MIT
License-File: LICENSE
Keywords: agent,ai,automation,llm
Classifier: Development Status :: 4 - Beta
Classifier: Intended Audience :: Developers
Classifier: Programming Language :: Python :: 3
Classifier: Programming Language :: Python :: 3.12
Requires-Python: >=3.12
Requires-Dist: aiofiles>=24.1.0
Requires-Dist: aiohttp>=3.12.15
Requires-Dist: art>=6.5
Requires-Dist: arxiv>=2.2.0
Requires-Dist: chunkr-ai>=0.1.0
Requires-Dist: colorlog>=6.9.0
Requires-Dist: docker>=7.1.0
Requires-Dist: google-genai>=1.26.0
Requires-Dist: hydra-core>=1.3.2
Requires-Dist: ipython>=9.5.0
Requires-Dist: jinja2>=3.1.6
Requires-Dist: matplotlib>=3.10.3
Requires-Dist: mcp>=1.12.3
Requires-Dist: openai-agents==0.3.3
Requires-Dist: openinference-instrumentation-openai-agents>=1.1.1
Requires-Dist: openinference-instrumentation-openai>=0.1.30
Requires-Dist: openpyxl>=3.1.5
Requires-Dist: pandas>=2.3.0
Requires-Dist: pexpect>=4.9.0
Requires-Dist: prompt-toolkit>=3.0.52
Requires-Dist: psycopg2-binary>=2.9.10
Requires-Dist: python-pptx>=1.0.2
Requires-Dist: requests>=2.32.4
Requires-Dist: rich>=14.1.0
Requires-Dist: sqlmodel>=0.0.24
Requires-Dist: tiktoken>=0.9.0
Requires-Dist: toml>=0.10.2
Requires-Dist: wikipedia-api>=0.8.1
Provides-Extra: litllm
Requires-Dist: litellm>=1.77.0; extra == 'litllm'
